libdiatonic/__init__.py
libdiatonic/_version.py
libdiatonic/meter/__init__.py
libdiatonic/meter/duration.py
libdiatonic/meter/measure.py
libdiatonic/pitch/__init__.py
libdiatonic/pitch/chord.py
libdiatonic/pitch/interval.py
libdiatonic/pitch/key.py
libdiatonic/pitch/mode.py
libdiatonic/pitch/note.py
libdiatonic-0.2.3.dist-info/LICENSE
libdiatonic-0.2.3.dist-info/METADATA
libdiatonic-0.2.3.dist-info/WHEEL
libdiatonic-0.2.3.dist-info/top_level.txt
libdiatonic-0.2.3.dist-info/RECORD
