Metadata-Version: 2.1
Name: libdiatonic
Version: 0.2.3
Summary: Library for modeling music theory constructs
Home-page: https://gitlab.com/ajk8/libdiatonic
Author: Adam Kaufman
Author-email: kaufman.blue@gmail.com
License: MIT
Download-URL: https://gitlab.com/ajk8/libdiatonic/repository/archive.tar.gz?ref=0.2.3
Keywords: music theory
Platform: UNKNOWN
Classifier: Development Status :: 3 - Alpha
Classifier: License :: OSI Approved :: MIT License
Classifier: Programming Language :: Python :: 3
Classifier: Programming Language :: Python :: 3.3
Classifier: Programming Language :: Python :: 3.4
Classifier: Programming Language :: Python :: 3.5
Requires-Dist: funcy (>=1.7)
